perpetual_context/__init__.py
perpetual_context/perpetual_context.py
perpetual_context-2.0.3.dist-info/LICENSE.txt
perpetual_context-2.0.3.dist-info/METADATA
perpetual_context-2.0.3.dist-info/WHEEL
perpetual_context-2.0.3.dist-info/top_level.txt
perpetual_context-2.0.3.dist-info/RECORD
