Metadata-Version: 2.2
Name: perpetual_context
Version: 2.0.3
Home-page: https://github.com/sapiens-technology/PerpetualContext
Author: OPENSAPI
License: Proprietary Software
License-File: LICENSE.txt
Requires-Dist: count-tokens
Requires-Dist: requests
Requires-Dist: numpy
Requires-Dist: openpyxl
Requires-Dist: pandas
Requires-Dist: statistics
Requires-Dist: certifi
Requires-Dist: tabulate
Requires-Dist: PyPDF2
Requires-Dist: PyMuPDF
Requires-Dist: python-docx
Requires-Dist: python-pptx
Requires-Dist: beautifulsoup4
Requires-Dist: youtube-search-python
Requires-Dist: youtube-transcript-api
Requires-Dist: pillow
Requires-Dist: easyocr
Requires-Dist: torch
Requires-Dist: torchvision
Requires-Dist: webcolors==1.13
Requires-Dist: scikit-learn
Requires-Dist: pydub
Requires-Dist: SpeechRecognition
Dynamic: author
Dynamic: home-page
Dynamic: license
Dynamic: requires-dist
